grid_utils/__init__.py
grid_utils/dimension.py
grid_utils/exceptions.py
grid_utils/gridder.py
grid_utils/interp.py
grid_utils/region.py
grid_utils/dimension/__init__.py
grid_utils/dimension/datetime_dim.py
grid_utils/dimension/grid_dim.py
grid_utils/dimension/indexed_array.py
grid_utils/dimension/indexer.py
grid_utils/dimension/meshgrid.py
grid_utils/dimension/xy_dim.py
grid_utils/dimension/grid_dim/__init__.py
grid_utils/dimension/grid_dim/datetime_dim.py
grid_utils/dimension/grid_dim/grid_dim.py
grid_utils/dimension/grid_dim/list_dim.py
grid_utils/dimension/grid_dim/mixins.py
grid_utils/dimension/grid_dim/xy_dim.py
grid_utils/tests/__init__.py
grid_utils/tests/test_GribGridder.py
grid_utils/tests/test_xy_tiler.py
grid_utils/tiler/__init__.py
grid_utils/tiler/xy_tiler.py
grid_utils-0.0.34.dist-info/LICENSE
grid_utils-0.0.34.dist-info/METADATA
grid_utils-0.0.34.dist-info/WHEEL
grid_utils-0.0.34.dist-info/top_level.txt
grid_utils-0.0.34.dist-info/RECORD
