Metadata-Version: 2.1
Name: grid-utils
Version: 0.0.34
Summary: Data grid related utils
Home-page: https://github.com/claydodo/grid_utils
Author: claydodo and his little friends (xiao huo ban)
Author-email: claydodo@foxmail.com
Classifier: Programming Language :: Python :: 2.7 
Classifier: Programming Language :: Python :: 3 
Classifier: Operating System :: OS Independent
License-File: LICENSE
Requires-Dist: numpy
